setup.py
Prubik/__init__.py
Prubik.egg-info/PKG-INFO
Prubik.egg-info/SOURCES.txt
Prubik.egg-info/dependency_links.txt
Prubik.egg-info/requires.txt
Prubik.egg-info/top_level.txt