Metadata-Version: 2.1
Name: Prubik
Version: 1.0
Summary: Build Your Own Rubika Bot !
Author: 0xRezA
Author-email: gg.test1386@gmail.com
Keywords: Rubika,Rubika Bot
Classifier: Programming Language :: Python :: 3.6
Classifier: Programming Language :: Python :: 3.7
Classifier: Programming Language :: Python :: 3.8
Classifier: Programming Language :: Python :: 3.9
Classifier: Programming Language :: Python :: 3.10
Classifier: Programming Language :: Python :: 3.11
Classifier: License :: OSI Approved :: MIT License
